[
    {
        "name": "Mercury",
        "radius": 2440,
        "texture": "static/img/textures/mercury.png",
        "distance": 57
    },
    {
        "name": "Venus",
        "radius": 6052,
        "texture": "static/img/textures/venus.png",
        "distance": 108
    },
    {
        "name": "Earth",
        "radius": 6378,
        "texture": "static/img/textures/earth.png",
        "distance": 150
    },
    {
        "name": "Mars",
        "radius": 3397,
        "texture": "static/img/textures/mars.png",
        "distance": 228
    },
    {
        "name": "Jupiter",
        "radius": 71492,
        "texture": "static/img/textures/jupiter.png",
        "distance": 779
    },
    {
        "name": "Saturn",
        "radius": 60268,
        "texture": "static/img/textures/saturn.png",
        "distance": 1430
    },
    {
        "name": "Uranus",
        "radius": 25559,
        "texture": "static/img/textures/uranus.png",
        "distance": 2880  
    },
    {
        "name": "Neptune",
        "radius": 24766,
        "texture": "static/img/textures/neptune.png",
        "distance": 4500  
    }
]
